lens_reasoning_sdk/__init__.py
lens_reasoning_sdk/exceptions.py
lens_reasoning_sdk/models.py
lens_reasoning_sdk/query_processor.py
lens_reasoning_sdk/steering_manager.py
lens_reasoning_sdk-1.0.0.dist-info/licenses/LICENSE
lens_reasoning_sdk-1.0.0.dist-info/METADATA
lens_reasoning_sdk-1.0.0.dist-info/WHEEL
lens_reasoning_sdk-1.0.0.dist-info/top_level.txt
lens_reasoning_sdk-1.0.0.dist-info/RECORD
