Metadata-Version: 2.4
Name: lens-reasoning-sdk
Version: 1.0.0
Summary: Python SDK for the Lens Reasoning System
Home-page: https://github.com/tupl-xyz/lens-sdk
Author: tupl
Author-email: TUPL Team <support@tupl.xyz>
License: MIT
Project-URL: Homepage, https://api.tupl.xyz
Project-URL: Repository, https://github.com/tupl-xyz/lens-reasoning-sdk
Keywords: ai,reasoning,lens,artificial-intelligence,sdk
Classifier: Development Status :: 4 - Beta
Classifier: Intended Audience :: Developers
Classifier: License :: OSI Approved :: MIT License
Classifier: Operating System :: OS Independent
Classifier: Programming Language :: Python :: 3
Classifier: Programming Language :: Python :: 3.8
Classifier: Programming Language :: Python :: 3.9
Classifier: Programming Language :: Python :: 3.10
Classifier: Programming Language :: Python :: 3.11
Classifier: Topic :: Scientific/Engineering :: Artificial Intelligence
Classifier: Topic :: Software Development :: Libraries :: Python Modules
Requires-Python: >=3.8
License-File: LICENSE
Requires-Dist: httpx>=0.25.0
Requires-Dist: pydantic>=2.0.0
Dynamic: author
Dynamic: home-page
Dynamic: license-file
Dynamic: requires-python
